freebox_api/__init__.py
freebox_api/access.py
freebox_api/aiofreepybox.py
freebox_api/api/__init__.py
freebox_api/api/airmedia.py
freebox_api/api/call.py
freebox_api/api/connection.py
freebox_api/api/dhcp.py
freebox_api/api/download.py
freebox_api/api/freeplug.py
freebox_api/api/fs.py
freebox_api/api/ftp.py
freebox_api/api/fw.py
freebox_api/api/home.py
freebox_api/api/lan.py
freebox_api/api/lcd.py
freebox_api/api/netshare.py
freebox_api/api/notifications.py
freebox_api/api/parental.py
freebox_api/api/phone.py
freebox_api/api/player.py
freebox_api/api/remote.py
freebox_api/api/rrd.py
freebox_api/api/storage.py
freebox_api/api/switch.py
freebox_api/api/system.py
freebox_api/api/tv.py
freebox_api/api/upnpav.py
freebox_api/api/upnpigd.py
freebox_api/api/wifi.py
freebox_api/constants.py
freebox_api/exceptions.py
freebox_api/freebox_certificates.pem
freebox_api/py.typed
freebox_api-1.2.2.dist-info/LICENSE.rst
freebox_api-1.2.2.dist-info/METADATA
freebox_api-1.2.2.dist-info/WHEEL
freebox_api-1.2.2.dist-info/entry_points.txt
freebox_api-1.2.2.dist-info/RECORD
