Metadata-Version: 2.1
Name: freebox-api
Version: 1.2.2
Summary: Provides asynchronous authentication and access to Freebox servers
Home-page: https://github.com/hacf-fr/freebox-api
License: GNU GPL v3
Keywords: freebox,iliadbox
Author: stilllman
Author-email: luc_touraille@yahoo.fr
Requires-Python: >=3.8.18,<4.0.0
Classifier: Development Status :: 5 - Production/Stable
Classifier: Framework :: AsyncIO
Classifier: Intended Audience :: Developers
Classifier: Intended Audience :: System Administrators
Classifier: License :: OSI Approved :: GNU General Public License (GPL)
Classifier: License :: Other/Proprietary License
Classifier: Operating System :: OS Independent
Classifier: Programming Language :: Python :: 3
Classifier: Programming Language :: Python :: 3.9
Classifier: Programming Language :: Python :: 3.10
Classifier: Programming Language :: Python :: 3.11
Classifier: Programming Language :: Python :: 3.12
Classifier: Programming Language :: Python :: 3.13
Classifier: Programming Language :: Python :: 3.8
Classifier: Topic :: Home Automation
Requires-Dist: aiohttp (>=3,<4)
Requires-Dist: importlib-metadata (>=3.3,<9.0) ; python_version < "3.12"
Requires-Dist: typing-extensions (>=3.8.18,<5.0.0) ; python_version >= "3.8" and python_version < "3.12"
Project-URL: Changelog, https://github.com/hacf-fr/freebox-api/releases
Project-URL: Documentation, https://freebox-api.readthedocs.io
Project-URL: Repository, https://github.com/hacf-fr/freebox-api
